AnquanKe2019q3/README.md
AnquanKe2019q3/__init__.py
AnquanKe2019q3/__main__.py
AnquanKe2019q3/file.pdf
AnquanKe2019q3/index.html
anquan_ke_2019q3-2024.3.4.0.dist-info/METADATA
anquan_ke_2019q3-2024.3.4.0.dist-info/WHEEL
anquan_ke_2019q3-2024.3.4.0.dist-info/entry_points.txt
anquan_ke_2019q3-2024.3.4.0.dist-info/top_level.txt
anquan_ke_2019q3-2024.3.4.0.dist-info/RECORD
